dagster_dask/__init__.py
dagster_dask/data_frame.py
dagster_dask/executor.py
dagster_dask/resources.py
dagster_dask/utils.py
dagster_dask/version.py
dagster_dask-1.0.5.dist-info/LICENSE
dagster_dask-1.0.5.dist-info/METADATA
dagster_dask-1.0.5.dist-info/WHEEL
dagster_dask-1.0.5.dist-info/top_level.txt
dagster_dask-1.0.5.dist-info/RECORD
