Metadata-Version: 2.1
Name: dagster-dask
Version: 1.0.5
Summary: Package for using Dask as Dagster's execution engine.
Home-page: https://github.com/dagster-io/dagster/tree/master/python_modules/libraries/dagster-dask
Author: Elementl
Author-email: hello@elementl.com
License: Apache-2.0
Platform: UNKNOWN
Classifier: Programming Language :: Python :: 3.7
Classifier: Programming Language :: Python :: 3.8
Classifier: Programming Language :: Python :: 3.9
Classifier: Programming Language :: Python :: 3.10
Classifier: License :: OSI Approved :: Apache Software License
Classifier: Operating System :: OS Independent
License-File: LICENSE
Requires-Dist: bokeh
Requires-Dist: dagster (==1.0.5)
Requires-Dist: dask[dataframe] (>=1.2.2)
Requires-Dist: distributed (>=1.28.1)
Provides-Extra: kube
Requires-Dist: dask-kubernetes ; extra == 'kube'
Provides-Extra: pbs
Requires-Dist: dask-jobqueue ; extra == 'pbs'
Provides-Extra: test
Requires-Dist: pyarrow ; extra == 'test'
Provides-Extra: yarn
Requires-Dist: dask-yarn ; extra == 'yarn'
